[
    {
        "title": "Comunidade quilombola no Paraná recebe oficina de artesanato",
        "url": "https://www.gov.br/iphan/pt-br/assuntos/noticias/comunidade-quilombola-no-parana-recebe-oficina-de-artesanato",
        "date": "2024-07-15",
        "category": "REFERÊNCIAS CULTURAIS",
        "tags": [],
        "content": "A comunidade da Restinga, no município da Lapa (PR), oferecerá uma oficina gratuita de artesanato quilombola, prevista para a próxima sexta-feira (19/07), às 14h. Promovida pelo Instituto do Patrimônio Histórico e Artístico Nacional (Iphan), a ação é aberta ao público, mediante inscrição por meio de formulário online. Os interessados podem se inscrever até o dia 18 de julho. \nA oficina será realizada em espaço da Associação Quilombola e Afrodescendente da Restinga e será conduzida pelas descendentes das antigas matriarcas da comunidade, Amélia e Setembrina - a professora Adriana Alexandre e as artesãs Cláudia Ferreira e Maria Aparecida Martins. Serão ensinadas técnicas de produção de cestos de palha, de milho e de bananeira; assim como de confecção de baixeiros, peças feitas com retalhos de tecidos e utilizadas abaixo das selas dos cavalos para proteger os lombos dos animais.\n\n\nOs baixeiros, usados abaixo das selas dos cavalos, estão associados às atividades tropeiras. (Foto: Iphan-PR)\nA oficina possibilitará uma imersão nos saberes e fazeres artesanais da comunidade remanescente de quilombo da Restinga que se relacionam com as atividades tropeiras na Lapa. Desde o século XVIII, os negócios dos tropeiros, com seu comércio de  mulas e outros animais de carga, fizeram parte do dia a dia de várias comunidades das regiões Sul e Sudeste do país.\n“Serão compartilhadas, ainda, as memórias e histórias das mulheres da comunidade a respeito do trabalho com artesanato na época em que a lida com as tropas de muares foi uma importante atividade econômica da região da Lapa”, explica a superintendente do Iphan-PR, Fabiana Martins.\nDurante a oficina, as etapas de produção das peças artesanais serão fotografadas e filmadas para compor a próxima exposição do Museu Casa Lacerda, em Lapa (PR), que abordará referências culturais negras do caminho das tropas na região. A mostra está prevista para setembro de 2024 e apresentará memórias e histórias sobre a participação das comunidades negras no ciclo do tropeirismo.\nA ideia de realizar uma exposição a partir desses saberes e fazeres quilombolas surgiu em 2023, após roda de conversa com lideranças da comunidade sobre as histórias e memórias da Restinga no Museu Casa Lacerda, realizada durante a programação da Primavera dos Museus.\nReferências culturais do tropeirismo\nOs ofícios, lugares e outros elementos associados ao tropeirismo na Lapa já foram objeto de Inventário Nacional de Referências Culturais (INRC)  realizado pelo Iphan, entre 2004 e 2006. O trabalho foi um desdobramento do tombamento do conjunto histórico da cidade, na década de 1990, que buscou produzir conhecimento sobre os bens imateriais locais. O levantamento teve como eixo o tropeirismo, considerando a relevância desse ciclo socioeconômico para a história da região. \nUma das referências identificadas no trabalho foi, por exemplo, o ofício do seleiro, detentor dos saberes da produção artesanal de artigos necessários à montaria, como o baixeiro. O INRC da Lapa, entretanto, limitou-se a identificar a ocorrência do ofício na sede do município, na antiga Rua das Tropas, onde os seleiros eram e são, na maioria, homens brancos”, aponta o analista de Patrimônio Cultural do Iphan-PR, Rafael Boeing. “Com a oficina e a exposição que será construída a partir dela, estamos buscando expandir o olhar sobre esta e outras referências culturais do tropeirismo, indo além do que foi identificado pelo Inventário e focando principalmente nas comunidades negras da Lapa, com destaque para a Restinga, onde os baixeiros são produzidos por mulheres negras”, complementa.\nServiçoOficina de artesanato quilombola - baixeiros e cestos de palhaData: 19 de julhoHorário: 14hLocal: Associação Quilombola e Afrodescendente da Restinga – BR 476, KM 189, Restinga – Lapa (PR)Inscrições: https://forms.gle/5uzKMDQ1ZKUk6E7EA Mais informações: (41) 3264-7971 | museucasalacerda@gmail.com\nMais informações para a imprensacomunicacao@iphan.gov.brLetícia Maciel - leticia.vale@iphan.gov.br\nwww.gov.br/iphanwww.facebook.com/Iphangov | www.twitter.com/IphanGovBrwww.instagram.com/iphangovbrwww.youtube.com/IphanGovBr"
    },
    {
        "title": "Iphan sediará II Seminário sobre os Estudos dos Problemas Urbanos de Brasília (DF)",
        "url": "https://www.gov.br/iphan/pt-br/assuntos/noticias/iphan-sediara-ii-seminario-sobre-os-estudos-dos-problemas-urbanos-de-brasilia-df",
        "date": "2024-07-15",
        "category": "EVENTO",
        "tags": [
            "Distrito Federal"
        ],
        "content": "Após 50 anos do primeiro debate sobre os estudos dos problemas urbanos de Brasília (DF), o Instituto do Patrimônio Histórico e Artístico Nacional (Iphan) sediará, entre os dias 6 e 8 de agosto, o II Seminário sobre os Estudos dos Problemas Urbanos de Brasília. O evento será realizado no auditório do Iphan Sede, na capital federal. Confira a programação do evento.\nO II Seminário sobre os Estudos dos Problemas Urbanos de Brasília contará com a presença de especialistas no assunto que vão discutir desde o direito à cidade para todas as pessoas, os desafios do planejamento e gestão urbana e territorial do Distrito Federal até como a capital deve enfrentar as mudanças climáticas. O evento é fruto de parceria entre Iphan, Andar a Pé, Instituto de Arquitetos do Brasil (IAB-DF), Universidade de Brasília (UnB), Conselho de Arquitetura e Urbanismo (CAU-DF), Ministério Público (MPDFT), Rede Urbanidade e Fórum de Defesa das Águas do Distrito Federal.\nNo primeiro seminário, realizado em 1974 no Senado Federal, os problemas da cidade foram debatidos com a ilustre presença do autor do Plano Piloto de Brasília, o urbanista Lucio Costa. Na ocasião, Lucio retornava à cidade depois da sua inauguração e discursou sobre “Considerações em torno do Plano Piloto de Brasília”, título de sua palestra, que contribuiu para criar condições para que essa área alcançasse sua plenitude e desenvolvimento. As contribuições dos arquitetos e urbanistas, engenheiros e parlamentares da época foram registradas em uma publicação que reúne estudos e debates sobre a urbanidade de Brasília.\nServiçoII Seminário sobre os Estudos dos Problemas Urbanos de BrasíliaSessão Solene - Senado FederalData: 05/08 Horário: 14h às 15h30\nDebates - Sede do IphanData: 06, 07 e 8/08 Horário: 9h às 18hLocal: Auditório do IphanEndereço: 702/902 Asa sul | Centro Empresarial Brasília 50, Torre A, Térreo, Brasília (DF)\nProgramação"
    }
]