[
    {
        "title": "Publicado edital de seleção de projetos de conectividade para escolas",
        "url": "https://www.gov.br/mec/pt-br/assuntos/noticias/2024/setembro/publicado-edital-de-selecao-de-projetos-de-conectividade-para-escolas",
        "date": "2024-09-04",
        "category": "ESCOLAS CONECTADAS",
        "tags": [
            "Ministério da Educação",
            "MEC",
            "Escolas Conectadas",
            "Educação Básica",
            "Edital",
            "Fust",
            "Fundo de Universalização dos Serviços de Telecomunicações"
        ],
        "content": "O Ministério das Comunicações (MCom) publicou nesta quarta-feira, 4 de setembro, o edital que viabiliza o investimento de até R$ 1,2 bilhão com potencial de levar internet de banda larga e Wi-Fi para cerca de 20 mil escolas públicas até 2026. O edital de seleção de renúncia fiscal do Fundo de Universalização dos Serviços de Telecomunicações (Fust) faz parte da Estratégia Nacional de Escolas Conectadas (Enec), uma parceria entre o MCom e o Ministério da Educação (MEC), e pertence ao Novo Programa de Aceleração do Crescimento (Novo PAC). \n\n\n\n\nLeia mais: Lançado edital de renúncia fiscal do Fust \n\n\n\n\nO objetivo da iniciativa é conectar todas as 138 mil escolas de ensino básico do país, com internet a ser utilizada em sala de aula para fins pedagógicos. A publicação determina que as propostas para a realização de projetos com potencial de levar conectividade às escolas devem ser submetidas no período de 6 a 16 de setembro de 2024. \n\n\nO investimento previsto no edital será de R$ 300 milhões em 2024, de R$ 450 milhões em 2025 e de R$ 450 milhões em 2026. \n\n\n“A operadora deixa de pagar o Fust e me entrega essa conectividade onde a rede dela já está passando. Então, só na renúncia fiscal, são R$ 1,2 bilhão para esses provedores e operadores entregarem 20 mil escolas conectadas”, disse o ministro das Comunicações, Juscelino Filho, em entrevista hoje ao programa Bom Dia, Ministro. \n\n\nLançamento – No evento de lançamento do edital, que aconteceu na última quarta-feira, 28 de agosto, o ministro das Comunicações ressaltou a importância da medida. De acordo com ele, o edital da renúncia fiscal tem uma dimensão grande dentro da estratégia do MCom. \n\n\n“Estamos dando liberdade às operadoras, aos provedores, para que escolham, uma a uma, as escolas. São três anos de renúncia e esperamos que, com isso, a gente consiga entregar a nossa meta”, finalizou. \n\n\nAs conexões serão realizadas por empresas de telecomunicações com seus próprios recursos, que poderão abater o investimento das contribuições ao fundo. Neste ano, as operadoras poderão usar até 40% do que contribuiriam para o Fust em conectar escolas. Tanto em 2025 quanto em 2026, esse percentual será de até 50%. \n\n\nA medida foi oficializada pelo presidente da República, Luiz Inácio Lula da Silva, por meio do Decreto nº 12.023/24, assinado em maio. Ele determina que o reconhecimento do benefício fiscal pode acontecer sem necessidade de intermediação do Banco Nacional de Desenvolvimento Econômico e Social (BNDES), que é atualmente o agente financeiro responsável pelo repasse de financiamentos reembolsáveis e não reembolsáveis a projetos feitos com dinheiro do Fust. \n\n\n \n\n\nAssessoria de Comunicação Social do MEC, com informações do MCom"
    },
    {
        "title": "MEC apresenta avanços ao CNE",
        "url": "https://www.gov.br/mec/pt-br/assuntos/noticias/2024/setembro/mec-apresenta-avancos-ao-cne",
        "date": "2024-09-04",
        "category": "PARTICIPAÇÃO SOCIAL",
        "tags": [
            "Ministério da Educação",
            "MEC",
            "Diálogo",
            "Participação Social",
            "Conselho Nacional de Educação",
            "CNE"
        ],
        "content": "O ministro de Estado da Educação, Camilo Santana, apresentou nesta quarta-feira, 4 de setembro, os avanços e as políticas prioritárias da Pasta aos membros do Conselho Nacional de Educação (CNE). Em agosto, 13 novos conselheiros tomaram posse no CNE representando a sociedade civil.  \n\n\n\n\nLeia Mais: MEC empossa novos membros do Conselho Nacional de Educação  \n\n\n\n\nParticiparam do encontro todos os secretários e as secretárias do MEC, presidentes das autarquias vinculadas e 22 conselheiros do CNE. O ministro Camilo Santana destacou o objetivo da reunião: aproximar o CNE do MEC, respeitando a autonomia do Conselho. “A ideia nessa reunião é apresentar a vocês o que o MEC tem pensado, quais são as nossas prioridades e conversarmos sobre de que forma podemos trabalhar cada vez mais sintonizados e próximos, com objetivo único de melhorar a educação deste país.” \n\n\nSantana enumerou as políticas prioritárias do MEC para a educação básica, a educação profissional e tecnológica (EPT) e a educação superior. Ele detalhou o Compromisso Nacional Criança Alfabetizada, o programa Escola em Tempo Integral, a Estratégia Nacional de Escolas Conectadas, o Pé-de-Meia e o Pacto Nacional pela Superação do Analfabetismo. Também abordou a conclusão de obras por meio do Novo Programa de Aceleração do Crescimento (Novo PAC), investimentos em transporte escolar e no Programa Nacional do Livro e do Material Didático (PNLD), além de ações para o fortalecimento da educação superior e da EPT. Relembrou a recomposição orçamentária das universidades e dos institutos federais (IFs), além da expansão com a criação de novos campi universitários e de IFs.  \n\n\nO ministro enfatizou a Política de Educação Especial na Perspectiva da Educação Inclusiva, investimentos em assistência estudantil, ações para formação de professores, entre outros temas. “Precisamos fazer mais encontros como este. Apresentamos uma visão geral do MEC. Os desafios são enormes em toda as áreas. Saúdo os conselheiros e conselheiras, pessoas que têm experiência. Reunimos aqui o que há de melhor para contribuir nesse processo de garantirmos a melhoria da qualidade da educação do nosso país”, afirmou. \n\n\nPor fim, Santana declarou que “o MEC está de portas abertas. Toda construção passa por diálogo. Democracia é respeitar as diferenças, mas construir consensos. As políticas de educação precisam ser políticas de Estado para que a gente possa deixar um legado para que não haja descontinuidade”. \n\n\nO presidente do CNE, André Lemos Jorge, agradeceu o espaço de diálogo. “Para nós é um sinal de muita honra estarmos aqui. O CNE está irmanado ao MEC nas políticas de qualidade do ensino para a construção de um país mais justo e igualitário. Estamos todos unidos pelo mesmo objetivo”, acrescentou. \n\n\nCNE – Órgão colegiado do MEC, o Conselho Nacional de Educação tem atribuições normativas, deliberativas e de assessoramento ao ministro da Educação no desempenho de suas funções, assim como atribuições do poder público federal em matéria de educação. Cada uma das Câmaras de Educação Básica e de Educação Superior, que compõem o CNE, é constituída  por 12 conselheiros.  \n\n\n \n\n\n\nAssessoria de Comunicação Social do MEC, com informações da Secretaria-Executiva (SE)"
    },
    {
        "title": "MEC participa de fórum da Undime sobre alfabetização",
        "url": "https://www.gov.br/mec/pt-br/assuntos/noticias/2024/setembro/mec-participa-de-forum-da-undime-sobre-alfabetizacao",
        "date": "2024-09-04",
        "category": "EDUCAÇÃO BÁSICA",
        "tags": [
            "Ministério da Educação",
            "MEC",
            "Educação Básica",
            "Alfabetização",
            "Tempo Integral",
            "Pé-de-Meia",
            "Rio Grande do Sul"
        ],
        "content": "O Ministério da Educação (MEC) participou nesta quarta-feira, 4 de setembro, do 34º Fórum Estadual de Educação do Rio Grande do Sul e Região Sul e do 1º Fórum Estadual de Alfabetização. Os encontros são promovidos pela União dos Dirigentes Municipais de Educação do Rio Grande do Sul (Undime-RS) e acontecem em Novo Hamburgo (RS). \n\n\nO ministro de Estado da Educação, Camilo Santana, foi representado no evento pelo secretário-executivo adjunto do MEC, Gregório Grisa, que destacou na abertura um conjunto de políticas do Ministério voltadas para a educação básica. Entre elas, está o Compromisso Nacional Criança Alfabetizada (CNCA), o Programa Escola em Tempo Integral e o Pé-de-Meia.  \n\n\nNo âmbito do CNCA, Grisa detalhou os eixos que compõem a política: gestão e governança; formação; infraestrutura física e pedagógica; reconhecimento de boas práticas; e sistemas de avaliação. Ele pontuou que estão disponíveis hoje mais de 7 mil Cantinhos da Leitura, em mais de 2.600 escolas no Rio Grande do Sul. “Agradeço o apoio da Undime e do estado, pois as metas do Compromisso são organizadas a partir do regime de colaboração e de corresponsabilização entre União, estados e municípios”, enfatizou. \n\n\nO secretário-executivo adjunto ainda colocou o MEC à disposição para aperfeiçoar e ampliar as ações ligadas à alfabetização na Região Sul do País. “Todas essas ações demonstram que estamos conseguindo concretizar, junto com o estado e os municípios, um conjunto de iniciativas para a alfabetização que não estavam presentes no passado recente. Estamos vivendo uma janela de oportunidade. Há um alinhamento e compromisso do governo federal em prol dessa etapa”, completou.  \n\n\nOs fóruns serão realizados até quinta-feira, 5 de setembro, e reúnem prefeitos, dirigentes municipais de educação, técnicos e equipes pedagógicas do Rio Grande do Sul, de Santa Catarina e do Paraná.  \n\n\n \n\n\nAssessoria de Comunicação Social do MEC, com informações da Secretaria-Executiva (SE)"
    },
    {
        "title": "Governo federal reúne as 21 escolas que se destacaram no Ideb",
        "url": "https://www.gov.br/mec/pt-br/assuntos/noticias/2024/setembro/governo-federal-reune-as-21-escolas-que-se-destacaram-no-ideb",
        "date": "2024-09-04",
        "category": "EDUCAÇÃO BÁSICA",
        "tags": [
            "Ministério da Educação",
            "MEC",
            "Índice de Desenvolvimento",
            "Educação Básica",
            "Ideb"
        ],
        "content": "O governo federal, por meio do Ministério da Educação (MEC), realizou nesta quarta-feira, 4 de setembro, um encontro com as 21 escolas que tiveram indicador 10 no Índice de Desenvolvimento da Educação Básica (ldeb) 2023 para o 5º ano do ensino fundamental. Estudantes, pais, responsáveis e representantes das escolas que se destacaram, bem como os secretários estaduais e municipais relacionados, foram recebidos pelo presidente da República, Luiz Inácio Lula da Silva, e pelo ministro de Estado da Educação, Camilo Santana. O encontro aconteceu no Palácio do Planalto, em Brasília (DF). \n\n\nO estado do Ceará teve 15 escolas com o maior Ideb. Em seguida, está Alagoas, com cinco, e Pernambuco, com uma. O Ideb foi divulgado pelo MEC em agosto. O desempenho das escolas e das redes de ensino é avaliado, entre outras estratégias, pelo Ideb. O indicador relaciona o desempenho dos estudantes em avaliações externas de larga escala com dados de fluxo escolar. \n\n\nNós queremos que todos os estados do Brasil tenham também escolas nota 10. Esse é um esforço de todos nós e para o qual estamos trabalhando.” Camilo Santana, ministro da Educação \n\n\nNo encontro, Lula lembrou que no passado via muitas notícias ruins sobre o Nordeste. Elas apontavam a região como a com o maior número de analfabetos, de evasão escolar, de crianças desnutridas. No entanto, segundo o presidente, essa realidade mudou, graças aos investimentos dos seus governos na educação. “Nós queremos que o mundo inteiro saiba que crianças brasileiras estudam, vencem na vida e que o Nordeste não é mais o símbolo do atraso. O Nordeste pode ser símbolo do desenvolvimento e da educação”, ressaltou.   \n\n\nPara o presidente da República, é necessário que todas as escolas do País conheçam as atividades e experiências desenvolvidas nas instituições com 10 pontos no Ideb, para que as boas práticas possam ser replicadas. “Agora, nós temos a tarefa de pegar o que acontece de fato dentro de uma escola como a de vocês, que motiva vocês a virarem nota 10, e o que acontece na escola de vocês nós precisamos garantir que aconteça em todas as escolas do Brasil”, disse.  \n\n\nLula ainda afirmou que quanto menos estudo, menos possibilidade de vencer na vida, de viver uma vida melhor: “E o que vocês estão me trazendo aqui é um exemplo de que é possível a gente virar este País de ponta-cabeça e fazer da educação a coisa mais importante. Não há, na história da humanidade, nenhum país que se desenvolveu sem antes fazer investimentos na educação, por isso é que, quando tomamos posse, em 2023, eu proibi utilizar a palavra ‘gasto’ em educação”. \n\n\nJá Santana destacou que o depoimento e as experiências de cada escola apresentados na cerimônia permitem que uns aprendam com os outros. “Fico muito feliz de receber aqui as 21 escolas que tiraram 10 no Ideb, que são todas do Nordeste brasileiro, de Alagoas, Pernambuco e do Ceará, mas nós queremos que todos os estados do Brasil tenham também escolas nota 10. Esse é um esforço de todos nós e para o qual estamos trabalhando”, ressaltou o ministro.  \n\n\nEle contou que, quando assumiu o Ministério da Educação, priorizou programas e ações voltados para a educação básica, pois o investimento do Brasil por aluno na educação superior está na média do que é investido pelos países desenvolvidos, enquanto, na educação básica, o investimento é um terço do que os países desenvolvidos investem.   \n\n\n“O maior sonho de um pai e de uma mãe é ver um futuro bom para os seus filhos, é ver seu filho na escola, aprender bem, ir para uma universidade, virar advogado, virar professor, médico. Esse é o sonho da gente”, afirmou.   \n\n\nRelatos – No encontro, representantes das escolas falaram sobre os desafios e as experiências exitosas para alcançar uma boa nota no Ideb. A secretária de Educação de Pires Ferreira (CE), Rosa Macedo, afirmou ser preciso que os educadores conheçam a realidade das crianças de perto, assim como de professores e colaboradores.  \n\n\n“O aluno não tem que estar só na escola. Você tem que conhecer ele na escola e após o muro da escola. A gente faz isso em Pires Ferreira, conhecemos cada aluno nosso, cada profissional, cada família, cada comunidade. Se a minha criança falta, eu vou buscar em casa, converso com a família, faço a busca ativa, contrato psicólogo, assistente social, mas eu vou buscar a minha criança”, contou.   \n\n\nMacedo ainda apontou a melhoria na vida dos alunos com a implantação do programa Escola em Tempo Integral. “Eu coloco uma turma em tempo integral e até a fisionomia da criança muda, porque ela é bem cuidada, ela toma banho, almoça, tem as quatro refeições necessárias, está aprendendo, sendo acompanhada, sendo vista, e isso é muito importante”, avaliou.  \n\n\nJá a diretora da Escola Teotônio Vilela de Alagoas, Andréa da Silva, representou os gestores e diretores de todas as escolas do estado que tiraram a nota máxima no Ideb. Segundo ela, essa foi a primeira vez que uma escola do campo está em destaque no Ideb e com uma nota tão boa. “Essa é uma experiência única nas nossas vidas”, disse a diretora, que começou a trabalhar como professora aos 19 anos de idade, na educação infantil.    \n\n\nAndréa da Silva apontou que na escola é realizado o projeto Por um Ideb Melhor Somos Todos um Só. “Esse projeto dá grandes resultados, porque são aplicados simulados padronizados mensalmente, não só no ano do Ideb. Nós vamos ter Ideb em 2025, mas o município já está fazendo em 2024. Além do simulado, nós temos as maratonas de aprendizagem. Todas essas ações sempre têm premiações para os alunos de destaque e os professores dos alunos”, contou. \n\n\nIdeb 2023 – De acordo com o ldeb 2023, o Brasil avançou nos anos iniciais do ensino fundamental, alcançando 6 pontos nessa etapa de ensino e atingindo a meta nacional estabelecida para o primeiro ciclo do indicador (2007-2021). Os anos finais do ensino fundamental (do 6º ao 9º ano) alcançaram 5 pontos, e o ensino médio registrou 4,3 pontos. Com isso, ambos ficaram abaixo das metas do indicador para o País nessas etapas, que era de 5,5 e 5,2, respectivamente. \n\n\n\n\nLeia mais: Ideb: Brasil avança nos anos iniciais do ensino fundamental \n\n\n\n\n\nConheça as 21 escolas com maior Ideb e suas séries históricas nos anos iniciais do ensino fundamental: \n\nEscola Municipal Nossa Senhora da Paz | Coreaú (CE) \n\n\n\n\n\n\n\n\n\nAno \n\n\n\n\n\n\n2005 \n\n\n\n\n\n\n2007 \n\n\n\n\n\n\n2009 \n\n\n\n\n\n\n2011 \n\n\n\n\n\n\n2013 \n\n\n\n\n\n\n2015 \n\n\n\n\n\n\n2017 \n\n\n\n\n\n\n2019 \n\n\n\n\n\n\n2021 \n\n\n\n\n\n\n2023 \n\n\n\n\n\n\n\n\nMeta \n\n\n\n\n\n\n- \n\n\n\n\n\n\n- \n\n\n\n\n\n\n- \n\n\n\n\n\n\n4,2 \n\n\n\n\n\n\n4,5 \n\n\n\n\n\n\n4,8 \n\n\n\n\n\n\n5,1 \n\n\n\n\n\n\n5,4 \n\n\n\n\n\n\n5,7 \n\n\n\n\n\n\n- \n\n\n\n\n\n\n\n\nIdeb \n\n\n\n\n\n\n- \n\n\n\n\n\n\n- \n\n\n\n\n\n\n4,0 \n\n\n\n\n\n\n4,5 \n\n\n\n\n\n\n5,7 \n\n\n\n\n\n\n8,7 \n\n\n\n\n\n\n8,1 \n\n\n\n\n\n\n6,7 \n\n\n\n\n\n\n7,9 \n\n\n\n\n\n\n10,0 \n\n\n\n\n\n\n\n\n\n  \n\n\nEscola de Ensino Fundamental (EEF) João Evangelista da Cruz | Cruz (CE) \n\n\n\n\n\n\n\n\n\nAno \n\n\n\n\n\n\n2005 \n\n\n\n\n\n\n2007 \n\n\n\n\n\n\n2009 \n\n\n\n\n\n\n2011 \n\n\n\n\n\n\n2013 \n\n\n\n\n\n\n2015 \n\n\n\n\n\n\n2017 \n\n\n\n\n\n\n2019 \n\n\n\n\n\n\n2021 \n\n\n\n\n\n\n2023 \n\n\n\n\n\n\n\n\nMeta \n\n\n\n\n\n\n- \n\n\n\n\n\n\n- \n\n\n\n\n\n\n- \n\n\n\n\n\n\n- \n\n\n\n\n\n\n6,2 \n\n\n\n\n\n\n6,4 \n\n\n\n\n\n\n6,6 \n\n\n\n\n\n\n6,9 \n\n\n\n\n\n\n7,1 \n\n\n\n\n\n\n- \n\n\n\n\n\n\n\n\nIdeb \n\n\n\n\n\n\n- \n\n\n\n\n\n\n- \n\n\n\n\n\n\n- \n\n\n\n\n\n\n6,0 \n\n\n\n\n\n\n- \n\n\n\n\n\n\n7,2 \n\n\n\n\n\n\n7,4 \n\n\n\n\n\n\n9,6 \n\n\n\n\n\n\n9,6 \n\n\n\n\n\n\n10,0 \n\n\n\n\n\n\n\n\n\n  \n\n\nEscola Macario José de Farias | Cruz (CE) \n\n\n\n\n\n\n\n\n\nAno \n\n\n\n\n\n\n2005 \n\n\n\n\n\n\n2007 \n\n\n\n\n\n\n2009 \n\n\n\n\n\n\n2011 \n\n\n\n\n\n\n2013 \n\n\n\n\n\n\n2015 \n\n\n\n\n\n\n2017 \n\n\n\n\n\n\n2019 \n\n\n\n\n\n\n2021 \n\n\n\n\n\n\n2023 \n\n\n\n\n\n\n\n\nMeta \n\n\n\n\n\n\n- \n\n\n\n\n\n\n- \n\n\n\n\n\n\n- \n\n\n\n\n\n\n- \n\n\n\n\n\n\n5,9 \n\n\n\n\n\n\n6,2 \n\n\n\n\n\n\n6,4 \n\n\n\n\n\n\n6,6 \n\n\n\n\n\n\n6,9 \n\n\n\n\n\n\n- \n\n\n\n\n\n\n\n\nIdeb \n\n\n\n\n\n\n- \n\n\n\n\n\n\n- \n\n\n\n\n\n\n- \n\n\n\n\n\n\n5,7 \n\n\n\n\n\n\n6,3 \n\n\n\n\n\n\n- \n\n\n\n\n\n\n7,6 \n\n\n\n\n\n\n8,5 \n\n\n\n\n\n\n9,7 \n\n\n\n\n\n\n10,0 \n\n\n\n\n\n\n\n\n\n  \n\n\nEscola de Educação Infantil e Ensino Fundamental (EEIEF) Renascer | Itapiúna (CE) \n\n\n\n\n\n\n\n\n\nAno \n\n\n\n\n\n\n2005 \n\n\n\n\n\n\n2007 \n\n\n\n\n\n\n2009 \n\n\n\n\n\n\n2011 \n\n\n\n\n\n\n2013 \n\n\n\n\n\n\n2015 \n\n\n\n\n\n\n2017 \n\n\n\n\n\n\n2019 \n\n\n\n\n\n\n2021 \n\n\n\n\n\n\n2023 \n\n\n\n\n\n\n\n\nMeta \n\n\n\n\n\n\n- \n\n\n\n\n\n\n- \n\n\n\n\n\n\n- \n\n\n\n\n\n\n3,4 \n\n\n\n\n\n\n3,7 \n\n\n\n\n\n\n4,0 \n\n\n\n\n\n\n4,3 \n\n\n\n\n\n\n4,6 \n\n\n\n\n\n\n4,9 \n\n\n\n\n\n\n- \n\n\n\n\n\n\n\n\nIdeb \n\n\n\n\n\n\n- \n\n\n\n\n\n\n- \n\n\n\n\n\n\n3,1 \n\n\n\n\n\n\n4,2 \n\n\n\n\n\n\n- \n\n\n\n\n\n\n4,2 \n\n\n\n\n\n\n6,1 \n\n\n\n\n\n\n6,5 \n\n\n\n\n\n\n7,6 \n\n\n\n\n\n\n10,0 \n\n\n\n\n\n\n\n\n\n  \n\n\nEscola Antonia Ferreira dos Santos | Mucambo (CE) \n\n\n\n\n\n\n\n\n\nAno \n\n\n\n\n\n\n2005 \n\n\n\n\n\n\n2007 \n\n\n\n\n\n\n2009 \n\n\n\n\n\n\n2011 \n\n\n\n\n\n\n2013 \n\n\n\n\n\n\n2015 \n\n\n\n\n\n\n2017 \n\n\n\n\n\n\n2019 \n\n\n\n\n\n\n2021 \n\n\n\n\n\n\n2023 \n\n\n\n\n\n\n\n\nMeta \n\n\n\n\n\n\n- \n\n\n\n\n\n\n- \n\n\n\n\n\n\n- \n\n\n\n\n\n\n- \n\n\n\n\n\n\n6,6 \n\n\n\n\n\n\n6,8 \n\n\n\n\n\n\n7,0 \n\n\n\n\n\n\n7,2 \n\n\n\n\n\n\n7,4 \n\n\n\n\n\n\n- \n\n\n\n\n\n\n\n\nIdeb \n\n\n\n\n\n\n- \n\n\n\n\n\n\n- \n\n\n\n\n\n\n- \n\n\n\n\n\n\n6,4 \n\n\n\n\n\n\n- \n\n\n\n\n\n\n- \n\n\n\n\n\n\n- \n\n\n\n\n\n\n7,9 \n\n\n\n\n\n\n9,5 \n\n\n\n\n\n\n10,0 \n\n\n\n\n\n\n\n\n\n  \n\n\nEscola José Domingos de Alcantara | Mucambo (CE) \n\n\n\n\n\n\n\n\n\nAno \n\n\n\n\n\n\n2005 \n\n\n\n\n\n\n2007 \n\n\n\n\n\n\n2009 \n\n\n\n\n\n\n2011 \n\n\n\n\n\n\n2013 \n\n\n\n\n\n\n2015 \n\n\n\n\n\n\n2017 \n\n\n\n\n\n\n2019 \n\n\n\n\n\n\n2021 \n\n\n\n\n\n\n2023 \n\n\n\n\n\n\n\n\nMeta \n\n\n\n\n\n\n- \n\n\n\n\n\n\n- \n\n\n\n\n\n\n- \n\n\n\n\n\n\n- \n\n\n\n\n\n\n7,1 \n\n\n\n\n\n\n7,3 \n\n\n\n\n\n\n7,5 \n\n\n\n\n\n\n7,7 \n\n\n\n\n\n\n7,8 \n\n\n\n\n\n\n- \n\n\n\n\n\n\n\n\nIdeb \n\n\n\n\n\n\n- \n\n\n\n\n\n\n- \n\n\n\n\n\n\n- \n\n\n\n\n\n\n7,0 \n\n\n\n\n\n\n- \n\n\n\n\n\n\n- \n\n\n\n\n\n\n- \n\n\n\n\n\n\n8,2 \n\n\n\n\n\n\n9,4 \n\n\n\n\n\n\n10,0 \n\n\n\n\n\n\n\n\n\n  \n\n\nEEF Francisco Severiano Sousa | Novo Oriente (CE) \n\n\n\n\n\n\n\n\n\nAno \n\n\n\n\n\n\n2005 \n\n\n\n\n\n\n2007 \n\n\n\n\n\n\n2009 \n\n\n\n\n\n\n2011 \n\n\n\n\n\n\n2013 \n\n\n\n\n\n\n2015 \n\n\n\n\n\n\n2017 \n\n\n\n\n\n\n2019 \n\n\n\n\n\n\n2021 \n\n\n\n\n\n\n2023 \n\n\n\n\n\n\n\n\nMeta \n\n\n\n\n\n\n- \n\n\n\n\n\n\n- \n\n\n\n\n\n\n- \n\n\n\n\n\n\n4,3 \n\n\n\n\n\n\n4,5 \n\n\n\n\n\n\n4,8 \n\n\n\n\n\n\n5,1 \n\n\n\n\n\n\n5,4 \n\n\n\n\n\n\n5,7 \n\n\n\n\n\n\n- \n\n\n\n\n\n\n\n\nIdeb \n\n\n\n\n\n\n- \n\n\n\n\n\n\n- \n\n\n\n\n\n\n4,0 \n\n\n\n\n\n\n5,2 \n\n\n\n\n\n\n5,3 \n\n\n\n\n\n\n8,4 \n\n\n\n\n\n\n7,9 \n\n\n\n\n\n\n6,7 \n\n\n\n\n\n\n8,1 \n\n\n\n\n\n\n10,0 \n\n\n\n\n\n\n\n\n\n  \n\n\nEscola de Ensino Médio em Tempo Integral (EEMTI) Francisco Ferreira Santiago | Piles Ferreira (CE) \n\n\n\n\n\n\n\n\n\nAno \n\n\n\n\n\n\n2005 \n\n\n\n\n\n\n2007 \n\n\n\n\n\n\n2009 \n\n\n\n\n\n\n2011 \n\n\n\n\n\n\n2013 \n\n\n\n\n\n\n2015 \n\n\n\n\n\n\n2017 \n\n\n\n\n\n\n2019 \n\n\n\n\n\n\n2021 \n\n\n\n\n\n\n2023 \n\n\n\n\n\n\n\n\nMeta \n\n\n\n\n\n\n- \n\n\n\n\n\n\n- \n\n\n\n\n\n\n- \n\n\n\n\n\n\n5,0 \n\n\n\n\n\n\n5,3 \n\n\n\n\n\n\n5,6 \n\n\n\n\n\n\n5,8 \n\n\n\n\n\n\n6,1 \n\n\n\n\n\n\n6,3 \n\n\n\n\n\n\n- \n\n\n\n\n\n\n\n\nIdeb \n\n\n\n\n\n\n- \n\n\n\n\n\n\n- \n\n\n\n\n\n\n4,7 \n\n\n\n\n\n\n5,7 \n\n\n\n\n\n\n5,9 \n\n\n\n\n\n\n8,6 \n\n\n\n\n\n\n7,7 \n\n\n\n\n\n\n- \n\n\n\n\n\n\n9,1 \n\n\n\n\n\n\n10,0 \n\n\n\n\n\n\n\n\n\n  \n\n\nEEMTI Alzira Maria de Araújo | Piles Ferreira (CE) \n\n\n\n\n\n\n\n\n\nAno \n\n\n\n\n\n\n2005 \n\n\n\n\n\n\n2007 \n\n\n\n\n\n\n2009 \n\n\n\n\n\n\n2011 \n\n\n\n\n\n\n2013 \n\n\n\n\n\n\n2015 \n\n\n\n\n\n\n2017 \n\n\n\n\n\n\n2019 \n\n\n\n\n\n\n2021 \n\n\n\n\n\n\n2023 \n\n\n\n\n\n\n\n\nMeta \n\n\n\n\n\n\n- \n\n\n\n\n\n\n- \n\n\n\n\n\n\n3,1 \n\n\n\n\n\n\n3,5 \n\n\n\n\n\n\n3,8 \n\n\n\n\n\n\n4,0 \n\n\n\n\n\n\n4,3 \n\n\n\n\n\n\n4,6 \n\n\n\n\n\n\n4,9 \n\n\n\n\n\n\n- \n\n\n\n\n\n\n\n\nIdeb \n\n\n\n\n\n\n- \n\n\n\n\n\n\n2,9 \n\n\n\n\n\n\n4,5 \n\n\n\n\n\n\n- \n\n\n\n\n\n\n- \n\n\n\n\n\n\n- \n\n\n\n\n\n\n7,3 \n\n\n\n\n\n\n8,4 \n\n\n\n\n\n\n8,3 \n\n\n\n\n\n\n10,0 \n\n\n\n\n\n\n\n\n\n  \n\n\nEscola Leonília Gomes Parente | Sobral (CE) \n\n\n\n\n\n\n\n\n\nAno \n\n\n\n\n\n\n2005 \n\n\n\n\n\n\n2007 \n\n\n\n\n\n\n2009 \n\n\n\n\n\n\n2011 \n\n\n\n\n\n\n2013 \n\n\n\n\n\n\n2015 \n\n\n\n\n\n\n2017 \n\n\n\n\n\n\n2019 \n\n\n\n\n\n\n2021 \n\n\n\n\n\n\n2023 \n\n\n\n\n\n\n\n\nMeta \n\n\n\n\n\n\n- \n\n\n\n\n\n\n- \n\n\n\n\n\n\n- \n\n\n\n\n\n\n7,0 \n\n\n\n\n\n\n7,2 \n\n\n\n\n\n\n7,3 \n\n\n\n\n\n\n7,5 \n\n\n\n\n\n\n7,7 \n\n\n\n\n\n\n7,8 \n\n\n\n\n\n\n- \n\n\n\n\n\n\n\n\nIdeb \n\n\n\n\n\n\n- \n\n\n\n\n\n\n- \n\n\n\n\n\n\n6,8 \n\n\n\n\n\n\n7,1 \n\n\n\n\n\n\n8,0 \n\n\n\n\n\n\n7,7 \n\n\n\n\n\n\n9,7 \n\n\n\n\n\n\n8,4 \n\n\n\n\n\n\n9,7 \n\n\n\n\n\n\n10,0 \n\n\n\n\n\n\n\n\n\n  \n\n\nEscola Raimundo Santana | Sobral (CE) \n\n\n\n\n\n\n\n\n\nAno \n\n\n\n\n\n\n2005 \n\n\n\n\n\n\n2007 \n\n\n\n\n\n\n2009 \n\n\n\n\n\n\n2011 \n\n\n\n\n\n\n2013 \n\n\n\n\n\n\n2015 \n\n\n\n\n\n\n2017 \n\n\n\n\n\n\n2019 \n\n\n\n\n\n\n2021 \n\n\n\n\n\n\n2023 \n\n\n\n\n\n\n\n\nMeta \n\n\n\n\n\n\n- \n\n\n\n\n\n\n- \n\n\n\n\n\n\n- \n\n\n\n\n\n\n5,6 \n\n\n\n\n\n\n5,8 \n\n\n\n\n\n\n6,1 \n\n\n\n\n\n\n6,3 \n\n\n\n\n\n\n6,5 \n\n\n\n\n\n\n6,8 \n\n\n\n\n\n\n- \n\n\n\n\n\n\n\n\nIdeb \n\n\n\n\n\n\n- \n\n\n\n\n\n\n- \n\n\n\n\n\n\n5,3 \n\n\n\n\n\n\n7,3 \n\n\n\n\n\n\n- \n\n\n\n\n\n\n8,4 \n\n\n\n\n\n\n7,9 \n\n\n\n\n\n\n8,3 \n\n\n\n\n\n\n7,9 \n\n\n\n\n\n\n10,0 \n\n\n\n\n\n\n\n\n\n  \n\n\nEscola Mocinha Rodrigues | Sobral (CE) \n\n\n\n\n\n\n\n\n\nAno \n\n\n\n\n\n\n2005 \n\n\n\n\n\n\n2007 \n\n\n\n\n\n\n2009 \n\n\n\n\n\n\n2011 \n\n\n\n\n\n\n2013 \n\n\n\n\n\n\n2015 \n\n\n\n\n\n\n2017 \n\n\n\n\n\n\n2019 \n\n\n\n\n\n\n2021 \n\n\n\n\n\n\n2023 \n\n\n\n\n\n\n\n\nMeta \n\n\n\n\n\n\n- \n\n\n\n\n\n\n4,5 \n\n\n\n\n\n\n4,9 \n\n\n\n\n\n\n5,3 \n\n\n\n\n\n\n5,5 \n\n\n\n\n\n\n5,8 \n\n\n\n\n\n\n6,0 \n\n\n\n\n\n\n6,3 \n\n\n\n\n\n\n6,5 \n\n\n\n\n\n\n- \n\n\n\n\n\n\n\n\nIdeb \n\n\n\n\n\n\n4,5 \n\n\n\n\n\n\n5,4 \n\n\n\n\n\n\n6,8 \n\n\n\n\n\n\n7,4 \n\n\n\n\n\n\n7,9 \n\n\n\n\n\n\n8,8 \n\n\n\n\n\n\n9,2 \n\n\n\n\n\n\n8,4 \n\n\n\n\n\n\n7,5 \n\n\n\n\n\n\n10,0 \n\n\n\n\n\n\n\n\n\n  \n\n\nEscola Antenor Naspolini | Sobral (CE) \n\n\n\n\n\n\n\n\n\nAno \n\n\n\n\n\n\n2005 \n\n\n\n\n\n\n2007 \n\n\n\n\n\n\n2009 \n\n\n\n\n\n\n2011 \n\n\n\n\n\n\n2013 \n\n\n\n\n\n\n2015 \n\n\n\n\n\n\n2017 \n\n\n\n\n\n\n2019 \n\n\n\n\n\n\n2021 \n\n\n\n\n\n\n2023 \n\n\n\n\n\n\n\n\nMeta \n\n\n\n\n\n\n- \n\n\n\n\n\n\n3,7 \n\n\n\n\n\n\n4,0 \n\n\n\n\n\n\n4,4 \n\n\n\n\n\n\n4,7 \n\n\n\n\n\n\n5,0 \n\n\n\n\n\n\n5,3 \n\n\n\n\n\n\n5,6 \n\n\n\n\n\n\n5,9 \n\n\n\n\n\n\n- \n\n\n\n\n\n\n\n\nIdeb \n\n\n\n\n\n\n3,6 \n\n\n\n\n\n\n5,0 \n\n\n\n\n\n\n6,0 \n\n\n\n\n\n\n6,8 \n\n\n\n\n\n\n6,9 \n\n\n\n\n\n\n8,8 \n\n\n\n\n\n\n8,4 \n\n\n\n\n\n\n8,1 \n\n\n\n\n\n\n7,1 \n\n\n\n\n\n\n10,0 \n\n\n\n\n\n\n\n\n\n  \n\n\nEscola Antônio Custodio de Azevedo | Sobral (CE) \n\n\n\n\n\n\n\n\n\nAno \n\n\n\n\n\n\n2005 \n\n\n\n\n\n\n2007 \n\n\n\n\n\n\n2009 \n\n\n\n\n\n\n2011 \n\n\n\n\n\n\n2013 \n\n\n\n\n\n\n2015 \n\n\n\n\n\n\n2017 \n\n\n\n\n\n\n2019 \n\n\n\n\n\n\n2021 \n\n\n\n\n\n\n2023 \n\n\n\n\n\n\n\n\nMeta \n\n\n\n\n\n\n- \n\n\n\n\n\n\n- \n\n\n\n\n\n\n- \n\n\n\n\n\n\n6,4 \n\n\n\n\n\n\n6,6 \n\n\n\n\n\n\n6,8 \n\n\n\n\n\n\n7,0 \n\n\n\n\n\n\n7,2 \n\n\n\n\n\n\n7,4 \n\n\n\n\n\n\n- \n\n\n\n\n\n\n\n\nIdeb \n\n\n\n\n\n\n- \n\n\n\n\n\n\n- \n\n\n\n\n\n\n6,1 \n\n\n\n\n\n\n7,0 \n\n\n\n\n\n\n8,3 \n\n\n\n\n\n\n9,7 \n\n\n\n\n\n\n9,8 \n\n\n\n\n\n\n8,8 \n\n\n\n\n\n\n9,2 \n\n\n\n\n\n\n10,0 \n\n\n\n\n\n\n\n\n\n  \n\n\nEEIEF Pedro Afrodisio Nogueira | Solonópole (CE) \n\n\n\n\n\n\n\n\n\nAno \n\n\n\n\n\n\n2005 \n\n\n\n\n\n\n2007 \n\n\n\n\n\n\n2009 \n\n\n\n\n\n\n2011 \n\n\n\n\n\n\n2013 \n\n\n\n\n\n\n2015 \n\n\n\n\n\n\n2017 \n\n\n\n\n\n\n2019 \n\n\n\n\n\n\n2021 \n\n\n\n\n\n\n2023 \n\n\n\n\n\n\n\n\nMeta \n\n\n\n\n\n\n- \n\n\n\n\n\n\n3,6 \n\n\n\n\n\n\n4,0 \n\n\n\n\n\n\n4,4 \n\n\n\n\n\n\n4,7 \n\n\n\n\n\n\n5,0 \n\n\n\n\n\n\n5,3 \n\n\n\n\n\n\n5,5 \n\n\n\n\n\n\n5,8 \n\n\n\n\n\n\n- \n\n\n\n\n\n\n\n\nIdeb \n\n\n\n\n\n\n3,6 \n\n\n\n\n\n\n3,1 \n\n\n\n\n\n\n4,0 \n\n\n\n\n\n\n6,0 \n\n\n\n\n\n\n5,4 \n\n\n\n\n\n\n6,1 \n\n\n\n\n\n\n7,1 \n\n\n\n\n\n\n6,4 \n\n\n\n\n\n\n7,1 \n\n\n\n\n\n\n10 \n\n\n\n\n\n\n\n\n\n  \n\n\nEscola Municipal Manoel Leandro de Morais | Custódia (PE) \n\n\n\n\n\n\n\n\n\nAno \n\n\n\n\n\n\n2005 \n\n\n\n\n\n\n2007 \n\n\n\n\n\n\n2009 \n\n\n\n\n\n\n2011 \n\n\n\n\n\n\n2013 \n\n\n\n\n\n\n2015 \n\n\n\n\n\n\n2017 \n\n\n\n\n\n\n2019 \n\n\n\n\n\n\n2021 \n\n\n\n\n\n\n2023 \n\n\n\n\n\n\n\n\nMeta \n\n\n\n\n\n\n- \n\n\n\n\n\n\n- \n\n\n\n\n\n\n- \n\n\n\n\n\n\n2,9 \n\n\n\n\n\n\n3,1 \n\n\n\n\n\n\n3,4 \n\n\n\n\n\n\n3,7 \n\n\n\n\n\n\n4,0 \n\n\n\n\n\n\n4,3 \n\n\n\n\n\n\n- \n\n\n\n\n\n\n\n\nIdeb \n\n\n\n\n\n\n- \n\n\n\n\n\n\n- \n\n\n\n\n\n\n2,6 \n\n\n\n\n\n\n4,9 \n\n\n\n\n\n\n5,4 \n\n\n\n\n\n\n6,0 \n\n\n\n\n\n\n5,5 \n\n\n\n\n\n\n6,4 \n\n\n\n\n\n\n8,6 \n\n\n\n\n\n\n10,0 \n\n\n\n\n\n\n\n\n\n  \n\n\nEscola de Educação Básica Vereador José Wilson Melo Nascimento | Coruripe (AL) \n\n\n\n\n\n\n\n\n\nAno \n\n\n\n\n\n\n2005 \n\n\n\n\n\n\n2007 \n\n\n\n\n\n\n2009 \n\n\n\n\n\n\n2011 \n\n\n\n\n\n\n2013 \n\n\n\n\n\n\n2015 \n\n\n\n\n\n\n2017 \n\n\n\n\n\n\n2019 \n\n\n\n\n\n\n2021 \n\n\n\n\n\n\n2023 \n\n\n\n\n\n\n\n\nMeta \n\n\n\n\n\n\n- \n\n\n\n\n\n\n- \n\n\n\n\n\n\n- \n\n\n\n\n\n\n4,4 \n\n\n\n\n\n\n4,7 \n\n\n\n\n\n\n4,9 \n\n\n\n\n\n\n5,2 \n\n\n\n\n\n\n5,5 \n\n\n\n\n\n\n5,8 \n\n\n\n\n\n\n- \n\n\n\n\n\n\n\n\nIdeb \n\n\n\n\n\n\n- \n\n\n\n\n\n\n- \n\n\n\n\n\n\n4,1 \n\n\n\n\n\n\n5,2 \n\n\n\n\n\n\n5,0 \n\n\n\n\n\n\n7,6 \n\n\n\n\n\n\n9,9 \n\n\n\n\n\n\n9,4 \n\n\n\n\n\n\n6,7 \n\n\n\n\n\n\n10,0 \n\n\n\n\n\n\n\n\n\n  \n\n\nEscola Municipal de Educação Básica Professora Maria Rocha Santos Silva | Coruripe (AL) \n\n\n\n\n\n\n\n\n\nAno \n\n\n\n\n\n\n2005 \n\n\n\n\n\n\n2007 \n\n\n\n\n\n\n2009 \n\n\n\n\n\n\n2011 \n\n\n\n\n\n\n2013 \n\n\n\n\n\n\n2015 \n\n\n\n\n\n\n2017 \n\n\n\n\n\n\n2019 \n\n\n\n\n\n\n2021 \n\n\n\n\n\n\n2023 \n\n\n\n\n\n\n\n\nMeta \n\n\n\n\n\n\n- \n\n\n\n\n\n\n- \n\n\n\n\n\n\n- \n\n\n\n\n\n\n5,1 \n\n\n\n\n\n\n5,3 \n\n\n\n\n\n\n5,6 \n\n\n\n\n\n\n5,9 \n\n\n\n\n\n\n6,1 \n\n\n\n\n\n\n6,4 \n\n\n\n\n\n\n- \n\n\n\n\n\n\n\n\nIdeb \n\n\n\n\n\n\n- \n\n\n\n\n\n\n- \n\n\n\n\n\n\n4,8 \n\n\n\n\n\n\n4,8 \n\n\n\n\n\n\n6,0 \n\n\n\n\n\n\n6,7 \n\n\n\n\n\n\n8,6 \n\n\n\n\n\n\n8,3 \n\n\n\n\n\n\n7,3 \n\n\n\n\n\n\n10,0 \n\n\n\n\n\n\n\n\n\n  \n\n\nEscola Municipal de Ensino Fundamental Integral Professora Marcia Neusilene da Trindade Batista | Teotônio Vilela (AL) \n\n\n\n\n\n\n\n\n\nAno \n\n\n\n\n\n\n2005 \n\n\n\n\n\n\n2007 \n\n\n\n\n\n\n2009 \n\n\n\n\n\n\n2011 \n\n\n\n\n\n\n2013 \n\n\n\n\n\n\n2015 \n\n\n\n\n\n\n2017 \n\n\n\n\n\n\n2019 \n\n\n\n\n\n\n2021 \n\n\n\n\n\n\n2023 \n\n\n\n\n\n\n\n\nMeta \n\n\n\n\n\n\n- \n\n\n\n\n\n\n- \n\n\n\n\n\n\n- \n\n\n\n\n\n\n3,8 \n\n\n\n\n\n\n4,1 \n\n\n\n\n\n\n4,4 \n\n\n\n\n\n\n4,7 \n\n\n\n\n\n\n5,0 \n\n\n\n\n\n\n5,3 \n\n\n\n\n\n\n- \n\n\n\n\n\n\n\n\nIdeb \n\n\n\n\n\n\n- \n\n\n\n\n\n\n- \n\n\n\n\n\n\n3,6 \n\n\n\n\n\n\n3,6 \n\n\n\n\n\n\n- \n\n\n\n\n\n\n6,3 \n\n\n\n\n\n\n7,0 \n\n\n\n\n\n\n8,9 \n\n\n\n\n\n\n9,6 \n\n\n\n\n\n\n10,0 \n\n\n\n\n\n\n\n\n\n  \n\n\nEscola Municipal de Educação Básica José Pereira de Andrade | Teotônio Vilela (AL) \n\n\n\n\n\n\n\n\n\nAno \n\n\n\n\n\n\n2005 \n\n\n\n\n\n\n2007 \n\n\n\n\n\n\n2009 \n\n\n\n\n\n\n2011 \n\n\n\n\n\n\n2013 \n\n\n\n\n\n\n2015 \n\n\n\n\n\n\n2017 \n\n\n\n\n\n\n2019 \n\n\n\n\n\n\n2021 \n\n\n\n\n\n\n2023 \n\n\n\n\n\n\n\n\nMeta \n\n\n\n\n\n\n- \n\n\n\n\n\n\n- \n\n\n\n\n\n\n- \n\n\n\n\n\n\n- \n\n\n\n\n\n\n- \n\n\n\n\n\n\n- \n\n\n\n\n\n\n6,8 \n\n\n\n\n\n\n7,0 \n\n\n\n\n\n\n7,2 \n\n\n\n\n\n\n- \n\n\n\n\n\n\n\n\nIdeb \n\n\n\n\n\n\n- \n\n\n\n\n\n\n- \n\n\n\n\n\n\n- \n\n\n\n\n\n\n- \n\n\n\n\n\n\n- \n\n\n\n\n\n\n6,6 \n\n\n\n\n\n\n6,4 \n\n\n\n\n\n\n9,1 \n\n\n\n\n\n\n9,7 \n\n\n\n\n\n\n10,0 \n\n\n\n\n\n\n\n\n\n  \n\n\nEscola Municipal Dr. José de Medeiros Sarmento | União dos Palmares (AL) \n\n\n\n\n\n\n\n\n\nAno \n\n\n\n\n\n\n2005 \n\n\n\n\n\n\n2007 \n\n\n\n\n\n\n2009 \n\n\n\n\n\n\n2011 \n\n\n\n\n\n\n2013 \n\n\n\n\n\n\n2015 \n\n\n\n\n\n\n2017 \n\n\n\n\n\n\n2019 \n\n\n\n\n\n\n2021 \n\n\n\n\n\n\n2023 \n\n\n\n\n\n\n\n\nMeta \n\n\n\n\n\n\n- \n\n\n\n\n\n\n- \n\n\n\n\n\n\n- \n\n\n\n\n\n\n3,3 \n\n\n\n\n\n\n3,6 \n\n\n\n\n\n\n3,8 \n\n\n\n\n\n\n4,1 \n\n\n\n\n\n\n4,5 \n\n\n\n\n\n\n4,8 \n\n\n\n\n\n\n- \n\n\n\n\n\n\n\n\nIdeb \n\n\n\n\n\n\n- \n\n\n\n\n\n\n- \n\n\n\n\n\n\n3,0 \n\n\n\n\n\n\n- \n\n\n\n\n\n\n4,5 \n\n\n\n\n\n\n- \n\n\n\n\n\n\n- \n\n\n\n\n\n\n7,3 \n\n\n\n\n\n\n8,5 \n\n\n\n\n\n\n10,0 \n\n\n\n\n\n\n\n\n\nFonte: Instituto Nacional de Estudos e Pesquisas Educacionais Anísio Teixeira (Inep) 2005-2023 \n\n\nIdeb – O Índice de Desenvolvimento da Educação Básica foi criado em 2007, para monitorar o desempenho da educação no Brasil. Ele reúne, em um só indicador, os resultados de duas dimensões: o fluxo escolar (Indicador Taxa de Aprovação) e as médias de desempenho nas avaliações de larga escala. O índice é calculado a partir do Censo Escolar e do Sistema de Avaliação da Educação Básica (Saeb). Varia de 0 a 10, de modo que quanto melhor o desempenho dos alunos e mais alto o número de aprovados, maior é o Ideb.  \n\n\nNo mesmo ano da criação do indicador (2007), foram pactuadas as metas pelo Compromisso Todos pela Educação (Decreto nº 6.094/2007), definidas para cada ente federado e unidade escolar de 2007 até 2021. O primeiro ciclo do Ideb se encerrou em 2021, com as seguintes metas: 6 para os anos iniciais do ensino fundamental, 5,5 para os anos finais e 5,5 para o ensino médio.   Em janeiro de 2024, o Instituto Nacional de Estudos e Pesquisas Educacionais Anísio Teixeira (Inep) instituiu um grupo técnico (GT), o GT Novo Ideb, com o objetivo de elaborar um estudo técnico para subsidiar o MEC na atualização do Índice e de novas metas para o Ideb. \n\n\n \n\n\nConfira o resultado do Ideb 2023 \n\n\nPanorama MEC (infográfico) \n\n\nTransmissão \n\n\nÁlbum de fotos \n\n\n\nAssessoria de Comunicação Social do MEC, com informações do Inep"
    },
    {
        "title": "Prouni 2/2024: último dia para entrega de documentos",
        "url": "https://www.gov.br/mec/pt-br/assuntos/noticias/2024/setembro/prouni-2-2024-ultimo-dia-para-entrega-de-documentos",
        "date": "2024-09-04",
        "category": "EDUCAÇÃO SUPERIOR",
        "tags": [
            "Ministério da Educação",
            "MEC",
            "Programa Universidade para Todos",
            "Prouni",
            "Segunda Chamada",
            "Documentação",
            "Prazo"
        ],
        "content": "Acaba nesta quarta-feira, 4 de setembro, o prazo para os candidatos pré-selecionados na segunda chamada do Programa Universidade para Todos (Prouni) apresentarem sua documentação às instituições de educação superior pretendidas. O Ministério da Educação (MEC) divulgou, no dia 23 de agosto, no Portal Único de Acesso ao Ensino Superior, o resultado da segunda chamada do processo seletivo do Programa Universidade para Todos (Prouni) referente ao segundo semestre de 2024.  \n\n\nDe acordo com o Edital nº 22/2024, que rege a seleção, o candidato pode fazer a entrega da documentação presencialmente ou por meio virtual, para comprovação das informações prestadas em sua inscrição. Nessa etapa, os pré-selecionados também podem ter de participar de processo seletivo próprio da instituição. As universidades e faculdades devem enviar ao candidato um comprovante de que a documentação foi recebida.  \n\n\nLista de espera – Aqueles que quiserem participar da lista de espera deverão manifestar seu interesse por meio da página do Prouni, nos dias 11 e 12 de setembro de 2024. A lista de espera estará disponível para as instituições de ensino superior no dia 17 de setembro. Os candidatos poderão consultá-la também na página do Prouni.   \n\n\nConfira o calendário completo do Prouni 2/2024: \n\n\n \n\n.\n\n\n\nProuni – Criado em 2004 pela Lei nº 11.096/2005, o Programa Universidade para Todos oferta bolsas de estudo integrais e parciais em cursos de graduação e sequenciais de formação específica em instituições de educação superior privadas. O Prouni ocorre duas vezes ao ano e tem como público-alvo o estudante sem diploma de nível superior.     \n\n\nEm 2024, o MEC ofertou 651.483 bolsas no Prouni, entre integrais (100%) e parciais (50%). Nas duas edições do ano, o programa teve 910.419 candidatos inscritos. Como cada participante pode escolher até dois cursos, o Prouni teve mais de 1,8 milhão de inscrições neste ano. \n\n\nAssessoria de Comunicação Social do MEC, com informações da Secretaria de Educação Superior (Sesu)"
    },
    {
        "title": "Inep cria diretoria de avaliação da EPT",
        "url": "https://www.gov.br/mec/pt-br/assuntos/noticias/2024/setembro/inep-cria-diretoria-de-avaliacao-da-ept",
        "date": "2024-09-04",
        "category": "EDUCAÇÃO PROFISSIONAL E TECNOLÓGICA",
        "tags": [
            "Ministério da Educação",
            "MEC",
            "Educação Profissional e Tecnológica",
            "EPT",
            "Inep",
            "Estrutura Regimental"
        ],
        "content": "O Instituto Nacional de Estudos e Pesquisas Educacionais Anísio Teixeira (Inep), autarquia vinculada ao Ministério da Educação (MEC), passa a contar com uma Diretoria de Avaliação da Educação Profissional e Tecnológica e com um Centro de Tecnologia, Inovação e Ciência de Dados. O Instituto teve sua estrutura regimental reformulada pelo Decreto nº 12.158/2024, publicado na terça-feira, 3 de setembro. O documento altera trechos do Decreto nº 11.204/2022 (que trata dessa organização), assim como remaneja e transforma o quadro demonstrativo dos cargos em comissão e das funções de confiança da autarquia. \n\n\nA nova diretoria do Inep será responsável por definir e propor parâmetros, critérios e mecanismos de realização das avaliações da educação profissional e tecnológica, bem como por realizar, em articulação com os sistemas federal, estaduais, distrital e municipais de ensino, as avaliações da EPT. Outra competência da Diretoria de Avaliação da Educação Profissional e Tecnológica é a produção e a disseminação de indicadores e de informações relacionados à avaliação da EPT. \n\n\nCentro de Tecnologia – Já o Centro de Tecnologia, Inovação e Ciência de Dados terá, entre outras competências, a de desenvolver mecanismos de disseminação de informações educacionais do Inep. Também cabe ao novo setor gerir dados relacionados às áreas responsáveis pelos processos de pesquisas, estudos e de avaliação educacional. Em suma, a área será incumbida das ações voltadas à inovação, no que diz respeito aos produtos desenvolvidos e aos dados produzidos pelo Instituto. \n\n\nInep – O Instituto Nacional de Estudos e Pesquisas Educacionais Anísio Teixeira foi criado em 1937, sob a denominação de “Instituto Nacional de Pedagogia”, e transformado em autarquia federal vinculada ao MEC em 1997. O Instituto é o órgão federal responsável pelas evidências educacionais e atua em três esferas: avaliações e exames educacionais; pesquisas estatísticas e indicadores educacionais; e gestão de conhecimento e estudos. \n\n\n \n\n\nAssessoria de Comunicação Social do MEC, com informações do Inep"
    }
]