[
    {
        "title": "ANEEL anuncia bandeira verde para o mês de fevereiro",
        "url": "https://www.gov.br/aneel/pt-br/assuntos/noticias/2024/aneel-anuncia-bandeira-verde-para-o-mes-de-fevereiro",
        "date": "2024-01-26",
        "category": "BANDEIRA TARIFÁRIA",
        "tags": [],
        "content": "A Agência Nacional de Energia Elétrica (ANEEL) anunciou nesta sexta-feira (26/1) que o mês de fevereiro terá bandeira tarifária verde. Significa que as contas de energia elétrica não terão custo adicional. A sinalização verde ocorre desde abril de 2022 porque as condições de geração de energia hidrelétrica em todo o país são favoráveis. São 22 meses seguidos de acionamento de bandeira verde.\nO diretor-geral da Agência, Sandoval Feitosa, destacou o cenário positivo para a geração de energia no País. “Com a geração em franca expansão, principalmente de fontes renováveis e limpas, alcançamos 22 meses seguidos de bandeira verde acionada. Sinal bastante positivo para o País que reflete condições favoráveis de geração de energia”, completou Feitosa.\nA ANEEL faz o monitoramento mensal e projeções de acionamento das bandeiras, válidas para todos os consumidores do Sistema Interligado Nacional (SIN), malha de linhas de transmissão de energia elétrica que conecta as usinas aos consumidores. O mecanismo das bandeiras tarifárias, que existe desde 2015, serve para demonstrar o custo real da geração de energia.\nExistem três tipos de bandeiras tarifárias: verde, amarela ou vermelha. Quer saber mais informações sobre bandeiras tarifárias? Assista o vídeo explicativo no nosso canal no youtube para compreender como são definidas as bandeiras tarifárias e não esqueça de se inscrever no nosso canal: https://www.youtube.com/watch?v=w1rS7_tGSvM&t=\nFicou com alguma dúvida? Acesse: https://www.gov.br/aneel/pt-br/assuntos/tarifas/bandeiras-tarifarias/faq-bandeiras-tarifarias."
    }
]