[
    {
        "title": "Governo Federal atende reivindicações do Grito da Terra",
        "url": "https://www.gov.br/secretariageral/pt-br/noticias/2024/maio/governo-federal-atende-reivindicacoes-do-grito-da-terra",
        "date": "2024-05-21",
        "category": "AGRICULTURA FAMILIAR",
        "tags": [
            "Grito da Terra",
            "Reivindicações",
            "CONTAG",
            "Agricultura Familiar",
            "Distrito Federal"
        ],
        "content": "“O Grito da Terra já foi o grito da dor dos que tombaram na luta pela reforma agrária, pela paz no campo, pela dignidade dos trabalhadores e trabalhadoras, já foi o grito da resistência e agora é o grito da reconstrução e união do nosso país”. Assim, o ministro-chefe da Secretaria-Geral da Presidência da República, Márcio Macêdo começou seu discurso no 24º Grito da Terra, organizado pela Confederação Nacional dos Trabalhadores Rurais Agricultores e Agricultoras Familiares, CONTAG, que traz reivindicações do setor ao governo federal.\nDesde 2023, a Secretaria-Geral da Presidência da República recebe antecipadamente, com o presidente da República, Luiz Inácio Lula da Silva, as demandas do Grito da Terra e articula com ministérios, as respostas para as principais necessidades do movimento. As iniciativas do governo federal compõem um caderno de respostas que fica disponível no site da SG para acompanhamento do movimento.\nDurante o ato, na Esplanada dos Ministérios, nesta terça-feira, o governo federal anunciou medidas como a criação um grupo de trabalho para incluir institucionalmente, na Secretaria-Geral, espaço para projetos e ações voltadas para a juventude no campo. Também foi divulgada a criação da quarta modalidade de compras governamentais de produtos da agricultura familiar. O Ministério da Saúde vai passar a comprar medicamentos e produtos fitoterápicos da agricultura familiar. Serão destinados R$ 40 milhões para a aquisição de medicamentos. Também foram anunciados R$ 19 milhões para a concessão de crédito fundiário para 580 famílias da Fazenda Aruanã no Ceará. Além disso, 10 mil famílias terão acesso a recursos para o fomento rural. O retorno do Programa Dom Helder Câmara com uma terceira fase para contribuir para a redução da pobreza rural, da insegurança alimentar e nutricional na agricultura familiar, além das desigualdades de gênero, geração e étnico-raciais, no Semiárido do Nordeste e de Minas Gerais com recursos de cerca de R$ 93 milhões para 30 mil famílias. O governo federal anunciou, ainda, a publicação de 49 editais de seleção de famílias para assentamento no programa nacional de Reforma Agrária.\nO ministro Paulo Teixeira, do Desenvolvimento Agrário e Agricultura Familiar lembrou os inúmeros agricultores familiares do Rio Grande do Sul atingidos pelas cheias que já duram 22 dias e relacionou os acontecimentos às mudanças climáticas no mundo todo. Teixeira enumerou várias ações já realizadas pelo governo federal em apoio aos atingidos pelas enchentes na zona rural do estado. “A hora é de optarmos por uma agricultura regenerativa. Se já tivéssemos feito essa opção, os impactos das chuvas teriam sido menores. De toda forma, estamos trabalhando para recuperar a capacidade produtiva dos agricultores e agricultoras gaúchas” disse Teixeira.\nO Presidente da CONTAG, Aristides Santos, ainda chamou o ministro Márcio Macêdo à frente do palco para agradecer o atendimento à pauta de reivindicações apresentada e pelo diálogo permanente proporcionado pelo ministério comandado por Macêdo."
    },
    {
        "title": "Gestores de juventude apresentam propostas de melhorias para o ID Jovem e para o Sistema Nacional de Juventude",
        "url": "https://www.gov.br/secretariageral/pt-br/noticias/2024/maio/gestores-de-juventude-apresentam-propostas-de-melhorias-para-o-id-jovem-e-para-o-sistema-nacional-de-juventude",
        "date": "2024-05-21",
        "category": "ID JOVEM | SINAJUVE",
        "tags": [
            "Gestores de juventude",
            "ID Jovem",
            "Sistema Nacional de Juventude"
        ],
        "content": "Gestores de políticas de juventude estão reunidos em Brasília desde segunda-feira (20), com o objetivo de fortalecer o diálogo com o governo federal e promover uma política de juventude que seja adequada à realidade de cada município, permitindo uma gestão mais eficiente e personalizada.\nO encontro faz parte da programação do 2º Seminário Nacional de Gestores e Gestoras Municipais de Juventude, promovido pela Secretaria Nacional de Juventude da Secretaria-Geral da Presidência da República. O encontro vai até amanhã, (22), possibilitando que gestores de políticas públicas de Juventude dos municípios tenham a oportunidade de interlocução com o governo federal.\nID JOVEM E SINAJUVE\nO segundo dia do evento começou com uma apresentação aos gestores municipais sobre as melhorias do programa ID Jovem e do Sinajuve, plataforma que reúne as políticas de juventude para uso dos gestores e conselheiros de juventude. A apresentação foi conduzida pelo diretor de políticas nacionais da SNJ, Nilson Florentino.\nO aperfeiçoamento dos dois programas faz parte da pesquisa de aprimoramento tecnológico, sob uma perspectiva humanista e inclusiva em prol da juventude brasileira, objeto do Termo de Execução Descentralizada nº 02/2023, que está sendo desenvolvido em parceria com o IFG - Instituto Federal de Goiás.\n\n\nFoto: Divulgação\n\nPARTICIPAÇÃO SOCIAL\nÀ tarde, os gestores estiveram reunidos em grupos para apresentarem propostas de melhorias para o ID JOVEM e para o SINAJUVE, que serão sistematizadas e apresentadas como parte da pesquisa.\nEm uma das salas, as problemáticas levantadas pelos gestores mostram que há uma necessidade maior de articulação dos gestores com outros poderes e uma maior divulgação, por exemplo, do ID Jovem, nas redes sociais.\nO gestor Thiago Lima, de Palmares, no Pernambuco, apontou para a necessidade da articulação intersetorial, divulgação dos programas e o monitoramento como três importantes gargalos. “Se a rede não funciona, não funciona o CadÚnico. É articulação, e as coisas só funcionam quando a gente dialoga. Outra questão é a comunicação, a divulgação nas redes sociais, que deve ser utilizada a nosso favor, e, por último, o monitoramento e fiscalização, através do diálogo dos conselhos de juventude com o Procon e o Ministério Público”, declarou.\nAtualmente, só é possível emitir a passagem de ônibus via ID Jovem diretamente do balcão das empresas de ônibus. A solução de emissão via internet foi uma das melhorias apontadas pelo grupo.\n“Moro no interior da Bahia e para emitir uma passagem é preciso ir até Salvador, gastando R$150 e correndo o risco de não conseguir emitir a passagem gratuita que o jovem pretendia”, explicou o gestor Cleiton Souza, de Serrolândia (BA).\nAs demais propostas destacaram articulação, com ênfase, no público da zona rural, que considere a realidade de cada município; a intersetorialidade; a realização de campanhas informativas dentro das escolas e institutos federais de divulgação e emissão da ID Jovem; a organização de um fórum para apresentação de dados sobre os atendimentos, recusas e reclamações contra empresas, entre outras questões."
    },
    {
        "title": "Sociedade civil apresenta propostas contra a fome e a pobreza em evento do G20 social na capital piauiense",
        "url": "https://www.gov.br/secretariageral/pt-br/noticias/2024/maio/sociedade-civil-apresenta-propostas-contra-a-fome-e-a-pobreza-em-evento-do-g20-social-na-capital-piauiense",
        "date": "2024-05-21",
        "category": "G20 SOCIAL",
        "tags": [
            "Piauí",
            "G20 SOCIAL",
            "g20",
            "sociedade civil"
        ],
        "content": "Muito além de receber um alimento e de comer, há diversas questões que devem ser levadas em consideração quando se fala no combate à fome e à pobreza. O encontro, que ocorreu nesta segunda-feira (20), no âmbito do G20 Social em Teresina, contou com um debate rico e com a contribuição da sociedade civil, apresentando várias óticas que perpassam o tema da fome e da pobreza.\nAs principais propostas encaminhadas pela sociedade civil brasileira serão levadas para a 3ª reunião da Força-Tarefa da Aliança Global Contra a Fome e a Pobreza, que ocorre também em Teresina, entre os dias 22 e 24 de maio.\nEntre as sugestões apresentadas estão: o fortalecimento da agricultura familiar; políticas de geração de renda e combate à fome; políticas de igualdade racial; segurança alimentar de pessoas celíacas e busca ativa por famílias em situação de vulnerabilidade com difícil acesso aos programas de governo.\nAlicerces da injustiça\nPara a presidente do Conselho Nacional de Segurança Alimentar e Nutricional (Consea), Elisabetta Recine, as contribuições da sociedade mostram que existem outros fatores, além da comida na mesa, que devem ser trabalhados para que a fome seja erradicada no mundo. “Quando se fala em acabar com a fome as pessoas acham que é entregar um alimento e ponto. Para acabar com a fome de fato, a gente precisa de uma mudança naquilo que gera fome, que é o racismo; a ausência do direito de ter terra e território; as desigualdades de gênero; as desigualdades geracionais. É isso que vai alimentando o dia a dia dessa injustiça”, afirmou.\nPacto transformador\nElisabetta Recine elencou, ainda, dois pontos importantes para o diálogo do G20 com a sociedade civil. \"Existem duas coisas que são divisores de águas para o desenvolvimento das nações: precisamos estabelecer um pacto entre os países para, não só acabar com a fome, mas seguirmos com a garantia da justiça social e da igualdade; e incentivar a participação social, pois, muitas vezes, os governos só procuram a sociedade quando precisam dela, como é o caso das eleições\", explicou.\nO ex-deputado Nazareno Fonteles, criador da Frente Parlamentar de Segurança Alimentar e Nutricional na Câmara Federal, foi homenageado durante o evento por sua atuação na frente e por ter sido o autor do Projeto de Lei n.º 3508, em 2012, que instituía a Renda Básica Familiar como garantia mínima do direito social à alimentação. O projeto foi incorporado à Constituição Federal por meio do Art. 6º e é considerado um dos embriões do Programa Fome Zero e do Bolsa Família.\n“Foram os anos mais gratificantes, que não foram ligados a votos, mas à garantia de direitos. A gente se emociona porque realmente foi muito bonito. Hoje tenho uma compreensão de um novo momento, não basta o direito à renda familiar, é preciso que o direito ao trabalho, ao emprego. Precisamos que uma política de pleno emprego seja instalada como política nacional”, declarou Fonteles."
    }
]