[
    {
        "title": "INPI publica nomeação de aprovados em concurso público",
        "url": "https://www.gov.br/inpi/pt-br/central-de-conteudo/noticias/inpi-publica-nomeacao-de-aprovados-em-concurso-publico",
        "date": "2024-08-27",
        "category": "No Category",
        "tags": [
            "gestão",
            "concurso"
        ],
        "content": "Foi publicada nesta terça-feira, dia 27 de agosto, no Diário Oficial da União, a Portaria INPI/PR nº143/2024, que nomeou os aprovados nas vagas previstas no Edital nº 1, de 30 de outubro de 2023.\nOs procedimentos admissionais estão em fase de finalização e a cerimônia de posse será nesta sexta-feira, dia 30 de agosto. As informações estão sendo transmitidas pelo canal de comunicação oficial com os aprovados.\nClique aqui e confira o teor da portaria."
    },
    {
        "title": "Inscrições abertas em cursos sobre uso da PI nos negócios",
        "url": "https://www.gov.br/inpi/pt-br/central-de-conteudo/noticias/inscricoes-abertas-em-cursos-sobre-uso-da-pi-nos-negocios",
        "date": "2024-08-27",
        "category": "No Category",
        "tags": [
            "capacitação",
            ""
        ],
        "content": "Estão abertas as inscrições para dois cursos sobre o uso da Propriedade Intelectual nos negócios, ofertados pela Academia de Propriedade Intelectual, Inovação e Desenvolvimento do INPI.\nO primeiro curso é voltado para negócios de base tradicional, sendo que o período de inscrição vai até 02 de setembro (ou até o preenchimento das vagas). A atividade será realizada entre 02 e 13 de setembro.\nO curso é online, gratuito e autoinstrucional, com carga horária de 12 h/a.\nPor sua vez, o segundo curso é voltado para negócios de base tecnológica, sendo que o período de inscrição vai até 02 de setembro (ou até o preenchimento das vagas). A atividade será realizada entre 02 e 27 de setembro.\nO curso também é online, gratuito e autoinstrucional, com carga horária de 20 h/a.\nPara mais informações, acesse a Agenda de Cursos."
    }
]