[
    {
        "title": "Brasil e China discutem cooperação em Propriedade Industrial",
        "url": "https://www.gov.br/inpi/pt-br/central-de-conteudo/noticias/brasil-e-china-discutem-cooperacao-em-propriedade-industrial",
        "date": "2024-08-19",
        "category": "No Category",
        "tags": [
            "cooperação",
            "propriedade industrial",
            "marcas",
            "patentes"
        ],
        "content": "O INPI e o Instituto Chinês de Propriedade Intelectual (CNIPA, na sigla em inglês) tiveram reunião no dia 16 de agosto, na sede do INPI, no Rio de Janeiro, para discutir a cooperação nesta área.\nEntre os temas em debate, estavam: o funcionamento do sistema de marcas no Brasil e a observância de tais direitos; as modalidades de exame prioritário de patentes, incluindo o acordo de Patent Prosecution Highway (PPH) entre os dois institutos; e o uso de ferramentas de Tecnologia da Informação, abarcando temas como inteligência artificial e cibersegurança. Outras temáticas abordadas na reunião foram o uso das Indicações Geográficas e a realização de atividades para a disseminação da PI.\nDurante a reunião, os dois institutos também trocaram informações sobre suas atividades, projetos e estrutura. Em relação à demanda de serviços, o CNIPA recebeu, em 2023, mais de 3 milhões de pedidos de patentes."
    }
]