[
    {
        "title": "Ministério do Trabalho e Emprego atualiza regras do Programa de Alimentação do Trabalhador (PAT)",
        "url": "https://www.gov.br/trabalho-e-emprego/pt-br/noticias-e-conteudo/2024/Outubro/ministerio-do-trabalho-e-emprego-atualiza-regras-do-programa-de-alimentacao-do-trabalhador-pat",
        "date": "2024-10-11",
        "category": "Programa de Alimentação do Trabalhador",
        "tags": [],
        "content": "O Ministério do Trabalho e Emprego (MTE) publicou hoje (10) uma nova Portaria que traz definições e restrições para o Programa de Alimentação do Trabalhador (PAT). A medida busca eliminar práticas irregulares, como o rebate, que envolve o uso de descontos ou outros benefícios não relacionados à saúde e segurança alimentar dos trabalhadores.\nA Portaria estabelece que as empresas participantes do PAT, que possuem contratos com fornecedores de alimentação, estão proibidas de exigir ou receber descontos sobre o valor acordado ou qualquer outro benefício indireto. Caso essa regra seja desrespeitada, as empresas podem ser multadas entre R$ 5 mil e R$ 50 mil pelos auditores-fiscais do MTE. Em caso de reincidência, o valor da multa dobra, podendo levar ao cancelamento da inscrição no PAT e à perda de benefícios fiscais.\nPrograma de Alimentação do Trabalhador -  O PAT conta, atualmente, com aproximadamente 469.161 empresas beneficiárias, 18.701 fornecedoras de alimentação coletiva e 35.447 nutricionistas cadastrados, alcançando um total de 21.961.737 trabalhadores beneficiados, dos quais aproximadamente 86% recebem até 5 salários-mínimos.\nA empresa beneficiária do Programa de Alimentação ao Trabalhador (PAT) é isenta de encargos sociais (contribuição para o Fundo de Garantia sobre o Tempo de Serviço (FGTS) e contribuição previdenciária). Além disso, o empregador optante pela tributação com base no lucro real pode deduzir parte das despesas com o PAT do imposto sobre a renda.\nO PAT tem como objetivo a melhoria das condições nutricionais dos trabalhadores visando à promoção da saúde e prevenção de doenças por meio da concessão de incentivos fiscais. Foi instituído pela Lei nº 6.321, de 14 de abril de 1976, e, atualmente, encontra-se regulamentado pelo Decreto n 10.854, de 10 de novembro de 2021, com instruções complementares estabelecidas pela Portaria MTP/GM nº 672, de 8 de novembro de 2021. O Programa busca atender prioritariamente os trabalhadores de baixa renda. \nAcesse a Portaria aqui. \nClique aqui e saiba mais sobre o PAT."
    }
]